fedibooster/__init__.py
fedibooster/app.py
fedibooster/boostable.py
fedibooster/config.py
fedibooster-2026.1.31.dist-info/WHEEL
fedibooster-2026.1.31.dist-info/entry_points.txt
fedibooster-2026.1.31.dist-info/METADATA
fedibooster-2026.1.31.dist-info/RECORD
