Metadata-Version: 2.3
Name: fedibooster
Version: 2026.1.31
Summary: Bot to boost/reblog posts with specified tags
Author: marvin8
Author-email: marvin8 <marvin8@tuta.io>
License: AGPL-3.0-or-later
Classifier: Development Status :: 5 - Production/Stable
Classifier: Environment :: Console
Classifier: Programming Language :: Python
Classifier: Programming Language :: Python :: 3.11
Classifier: Programming Language :: Python :: 3.12
Classifier: Programming Language :: Python :: 3.13
Requires-Dist: diskcache~=5.6.3
Requires-Dist: h11~=0.16.0
Requires-Dist: h2~=4.3.0
Requires-Dist: httpx~=0.28.1
Requires-Dist: loguru~=0.7.3
Requires-Dist: minimal-activitypub~=1.5.5
Requires-Dist: msgspec~=0.20.0
Requires-Dist: stamina~=25.2.0
Requires-Dist: tomli-w~=1.2.0
Requires-Dist: typer~=0.21.1
Requires-Python: >=3.11, <3.14
